twisted/plugins/vumi_worker_starter.py
vumi/__init__.py
vumi/config.py
vumi/connectors.py
vumi/errors.py
vumi/log.py
vumi/message.py
vumi/multiworker.py
vumi/reconnecting_client.py
vumi/rpc.py
vumi/sentry.py
vumi/service.py
vumi/servicemaker.py
vumi/utils.py
vumi/worker.py
vumi/application/__init__.py
vumi/application/base.py
vumi/application/http_relay.py
vumi/application/rapidsms_relay.py
vumi/application/sandbox.py
vumi/application/sandbox_rlimiter.py
vumi/application/sandboxer.js
vumi/application/session.py
vumi/application/tests/__init__.py
vumi/application/tests/app.js
vumi/application/tests/app_delayed_requests.js
vumi/application/tests/app_requires_path.js
vumi/application/tests/helpers.py
vumi/application/tests/test_base.py
vumi/application/tests/test_http_relay.py
vumi/application/tests/test_rapidsms_relay.py
vumi/application/tests/test_sandbox.py
vumi/application/tests/test_sandbox_rlimiter.py
vumi/application/tests/test_session.py
vumi/application/tests/test_test_helpers.py
vumi/blinkenlights/__init__.py
vumi/blinkenlights/message20110707.py
vumi/blinkenlights/message20110818.py
vumi/blinkenlights/metrics.py
vumi/blinkenlights/metrics_workers.py
vumi/blinkenlights/heartbeat/__init__.py
vumi/blinkenlights/heartbeat/monitor.py
vumi/blinkenlights/heartbeat/publisher.py
vumi/blinkenlights/heartbeat/storage.py
vumi/blinkenlights/heartbeat/tests/__init__.py
vumi/blinkenlights/heartbeat/tests/test_monitor.py
vumi/blinkenlights/heartbeat/tests/test_publisher.py
vumi/blinkenlights/heartbeat/tests/test_storage.py
vumi/blinkenlights/tests/__init__.py
vumi/blinkenlights/tests/test_message20110707.py
vumi/blinkenlights/tests/test_message20110818.py
vumi/blinkenlights/tests/test_metrics.py
vumi/blinkenlights/tests/test_metrics_workers.py
vumi/codecs/__init__.py
vumi/codecs/ivumi_codecs.py
vumi/codecs/vumi_codecs.py
vumi/codecs/tests/__init__.py
vumi/codecs/tests/test_vumi_codecs.py
vumi/components/__init__.py
vumi/components/message_formatters.py
vumi_seidu626-0.6.17.dist-info/AUTHORS
vumi_seidu626-0.6.17.dist-info/LICENSE
vumi_seidu626-0.6.17.dist-info/METADATA
vumi_seidu626-0.6.17.dist-info/WHEEL
vumi_seidu626-0.6.17.dist-info/top_level.txt
vumi_seidu626-0.6.17.dist-info/RECORD
